<?xml version="1.0" encoding="UTF-8"?>
<beans xmlns="http://www.springframework.org/schema/beans"
	xmlns:xsi="http://www.w3.org/2001/XMLSchema-instance" xmlns:util="http://www.springframework.org/schema/util"
	xsi:schemaLocation="http://www.springframework.org/schema/beans http://www.springframework.org/schema/beans/spring-beans-2.0.xsd
	http://www.springframework.org/schema/util http://www.springframework.org/schema/util/spring-util-2.0.xsd">


	<!-- +++++++++++++++++++++++++++++++++++++++ -->
	<!-- MODULE SETTINGS -->
	<!-- +++++++++++++++++++++++++++++++++++++++ -->

	<!-- MODULE: PROPERTIES -->
	<bean id="moduleProperties" class="org.springframework.beans.factory.config.MapFactoryBean">
		<property name="sourceMap">
			<map>
				<entry key="module.name" value="Wordsearch" />
				<entry key="module.version" value="1" />
				<entry key="module.author" value="James Stone" />
				<entry key="module.description" value="Play Wordsearch where difficulty adjusts to performance" />
				<entry key="module.execution.display.classname" value="ch.tatool.core.display.swing.SwingExecutionDisplayProvider" />
				<entry key="module.execution.initializer.classname" value="ch.tatool.core.module.initializer.SpringExecutorInitializer" />
				<entry key="module.execution.display.regionsContainer" value="true" />
				<entry key="module.scheduler.classname" value="ch.tatool.core.module.scheduler.AlwaysAllowModuleScheduler" />
				<entry key="module.info.classname" value="ch.tatool.app.gui.ModuleInfoPanel" />
			</map>
		</property>
	</bean>

	<!-- MODULE: EXPORTERS -->
	<bean id="moduleExporters" class="org.springframework.beans.factory.config.MapFactoryBean">
		<property name="sourceMap">
			<map>
				<entry key="localExporter">
					<bean class="ch.tatool.app.export.FileDataExporter">
						<property name="incrementalExport" value="false" />
						<property name="autoExport" value="false" />
					</bean>
				</entry>
			</map>
		</property>
	</bean>


	<!-- +++++++++++++++++++++++++++++++++++++++ -->
	<!-- GENERAL SETTINGS -->
	<!-- +++++++++++++++++++++++++++++++++++++++ -->

	<!-- KEYBOARD HANDLER -->
	<bean id="keyHandler" class="ch.tatool.core.element.handler.EscapeKeyEventHandler">
		<!-- allow to exit module by pressing ESCAPE -->
		<property name="allowEscapeKey" value="true" />
	</bean>

	<!-- STATUS PANEL ON -->
	<bean id="status_panel_on"
		class="ch.tatool.core.display.swing.status.DefaultModuleStatusRegionConfigurator">
		<property name="panels">
			<list>
				<util:constant
					static-field="ch.tatool.core.display.swing.status.StatusPanel.STATUS_PANEL_TIMER" />
				<util:constant 
					static-field="ch.tatool.core.display.swing.status.StatusPanel.STATUS_PANEL_OUTCOME" />
				<util:constant 
					static-field="ch.tatool.core.display.swing.status.StatusPanel.STATUS_PANEL_TRIAL" />
				<util:constant 
					static-field="ch.tatool.core.display.swing.status.StatusPanel.STATUS_PANEL_LEVEL" />
				<util:constant 
					static-field="ch.tatool.core.display.swing.status.StatusPanel.STATUS_PANEL_CUSTOM_ONE" />
			</list>
		</property>
	</bean>

	<!-- STATUS PANEL OFF -->
	<bean id="status_panel_off"
		class="ch.tatool.core.display.swing.status.DefaultModuleStatusRegionConfigurator">
		<property name="panels">
			<list>
			</list>
		</property>
	</bean>
	
	<!-- Start of trial pause (get ready) -->
	<!-- displays a 'get ready' message for given duration prior to start of each trial -->
	<bean id="get-ready" class="ch.tatool.core.executable.HTMLExecutable">
		<property name="base" value="/instructions/" />
		<property name="pages">
			<list>
				<value>getReady.html</value>
			</list>
		</property>
		<property name="duration" value="1000" />
	</bean>


	<!-- +++++++++++++++++++++++++++++++++++++++ -->
	<!-- ITERATOR SETTINGS -->
	<!-- +++++++++++++++++++++++++++++++++++++++ -->

	<!-- TASK ITERATORS -->

	<bean id="iter_ws" class="ch.tatool.core.element.TemporalListSelector">
		<!-- number of iterations -->
		<property name="numIterations" value="99" />
		<property name="timeout" value="120000" />
	</bean>

	<!-- +++++++++++++++++++++++++++++++++++++++ -->
	<!-- TASK SETTINGS -->
	<!-- +++++++++++++++++++++++++++++++++++++++ -->

	<!-- WMP -->

	<bean id="wordsearch" class="stone.javatasks.control.executables.WordsearchTrial">
		<property name="StartingSizeOfGrid" value="8" /> <!-- this number + 1 is the N in the NxN grid created to accomodate the wordsearch.-->
		<property name="TimerLimit" value="120" /> <!-- in seconds -->
	</bean>

	<!-- +++++++++++++++++++++++++++++++++++++++ -->
	<!-- MODULE HIERARCHY -->
	<!-- +++++++++++++++++++++++++++++++++++++++ -->

	<bean id="moduleHierarchy" class="ch.tatool.core.element.ListElement">

		<property name="handlers">
			<list>
				<bean id="main_iterator" class="ch.tatool.core.element.IteratedListSelector" />
				<bean class="ch.tatool.core.element.handler.pause.DefaultExecutionPauseHandler">
					<!-- interval between elements in milliseconds -->
					<property name="defaultInterElementPauseDuration" value="250" />
				</bean>
				<bean class="ch.tatool.core.element.handler.ExecutionFeedbackHandler" />
				<bean class="ch.tatool.core.element.handler.StatusPanelStateHandler">
					<property name="resetIds">
						<list>
							<util:constant static-field="ch.tatool.core.display.swing.status.StatusPanel.STATUS_PANEL_OUTCOME" />
						</list>
					</property>
					<property name="enableIds">
						<list>
							<util:constant static-field=
							"ch.tatool.core.display.swing.status.StatusPanel.STATUS_PANEL_TIMER" />
							<util:constant static-field="ch.tatool.core.display.swing.status.StatusPanel.STATUS_PANEL_OUTCOME" />
							<util:constant static-field="ch.tatool.core.display.swing.status.StatusPanel.STATUS_PANEL_TRIAL" />
							<util:constant static-field="ch.tatool.core.display.swing.status.StatusPanel.STATUS_PANEL_CUSTOM_ONE" />
						</list>
					</property>
					<property name="phase">
						<util:constant static-field="ch.tatool.exec.ExecutionPhase.PRE_PROCESS" />
					</property>
				</bean>
				<ref bean="keyHandler" />
			</list>
		</property>

		<property name="children">
			<list>
				<!-- WMP -->
				<!-- instruction -->
				<bean class="ch.tatool.core.element.ExecutableElement">
					<property name="executable">
						<bean class="stone.javatasks.helperclasses.HTMLExecutable">
							<property name="base" value="/instructions/Wordsearch/" />
							<property name="pages">
								<list>
									<value>WordsearchInstructions.html</value>
								</list>
							</property>
						</bean>
					</property>
				</bean>

				<!-- GET READY TEXT -->
				<bean class="ch.tatool.core.element.ExecutableElement">
					<property name="executable">
						<ref bean="get-ready" />
					</property>
				</bean>	


				<!-- Main Task -->
				
				<bean id="runSudoSession" class="ch.tatool.core.element.ListElement">
					<property name="handlers">
						<list>
							<ref bean="iter_ws" />
						</list>
					</property>

					<property name="children">
						<list>
						
							<!-- status panel on -->
							<bean class="ch.tatool.core.element.ExecutableElement">
								<property name="executable">
									<ref bean="status_panel_on" />
								</property>
							</bean>

							<bean class="ch.tatool.core.element.ExecutableElement">
								<property name="id" value="exec" />
								<property name="handlers">
									<list>
										<bean class="ch.tatool.core.element.handler.TrialCountHandler" />
										<bean class="ch.tatool.core.element.handler.DefaultTrialCountEvaluator" />
										<bean id="level" class="ch.tatool.core.element.handler.score.DefaultPointsAndLevelHandler">
											<property name="description" value="sudo session" />
											<property name="sampleSize" value="3" />
											<property name="minThreshold" value="100" />
											<property name="maxThreshold" value="100" />
										</bean>
										<bean class="ch.tatool.core.element.handler.score.UserFeedbackLevelListener">
											<property name="levelUpText" value="Well Done. The level will increase!"  />
											<property name="levelDownText" value="The level will drop by one"/>
										</bean>
										<bean class="ch.tatool.core.element.handler.timeout.DefaultVisualTimeoutHandler" >
											<property name="defaultTimerDuration" value="120000" />
										</bean>		
									</list>
								</property>
								<property name="executable">
									<ref bean="wordsearch" />
								</property>
							</bean>

						</list>
					</property>
				</bean>
				<!-- END OF BLOCK -->
				<bean class="ch.tatool.core.element.ExecutableElement">
					<property name="executable">
						<bean class="ch.tatool.core.executable.HTMLExecutable">
							<property name="base" value="/instructions/" />
							<property name="pages">
								<list>
									<value>endOfBlock.htm</value>
								</list>
							</property>
						</bean>
					</property>
				</bean>

				<!-- END -->
				<bean class="ch.tatool.core.element.ExecutableElement">
					<property name="executable">
						<bean class="ch.tatool.core.executable.HTMLExecutable">
							<property name="base" value="/instructions/" />
							<property name="pages">
								<list>
									<value>endOfModule.htm</value>
								</list>
							</property>
						</bean>
					</property>
				</bean>
			</list>
		</property>
	</bean>
</beans>